{
  "appInfo" : {
    "build" : "233.14015.106",
    "buildDate" : "2024-01-25T05:01:00Z[UTC]",
    "productCode" : "IC",
    "generated" : "2025-03-15T08:06:55.153511Z",
    "os" : "macOS 13.5.2",
    "runtime" : "JetBrains s.r.o. 17.0.9 17.0.9+7-b1087.11"
  },
  "runtimeInfo" : {
    "maxMemory" : 2147483648,
    "numberOfProcessors" : 10,
    "maxNumberOfIndexingThreads" : 9,
    "maxSizeOfFileForIntelliSense" : 2560000,
    "maxSizeOfFileForContentLoading" : 20971520
  },
  "type" : "Scanning",
  "projectIndexingActivityHistory" : {
    "projectName" : "ssss",
    "times" : {
      "scanningReason" : "On project open",
      "scanningType" : "FULL_ON_PROJECT_OPEN",
      "scanningId" : 0,
      "creatingIteratorsTime" : 72338000,
      "concurrentHandlingWallTimeWithoutPauses" : 1826978000,
      "concurrentHandlingWallTimeWithPauses" : 1826978000,
      "concurrentHandlingSumOfThreadTimesWithPauses" : 3036230750,
      "concurrentIterationAndScannersApplicationSumOfThreadTimesWithPauses" : 1220234335,
      "concurrentFileCheckSumOfThreadTimesWithPauses" : 1811206292,
      "delayedPushPropertiesStageTime" : 126000,
      "indexExtensionsTime" : 0,
      "dumbWallTimeWithPauses" : 0,
      "dumbWallTimeWithoutPauses" : 0,
      "updatingStart" : "2025-03-15T08:06:53.234656Z",
      "updatingEnd" : "2025-03-15T08:06:55.15041Z",
      "totalWallTimeWithPauses" : 1915745125,
      "wallTimeOnPause" : 0,
      "wasInterrupted" : false,
      "totalWallTimeWithoutPauses" : 1915745125
    },
    "fileCount" : {
      "numberOfFileProviders" : 8,
      "numberOfScannedFiles" : 42846,
      "numberOfFilesIndexedByInfrastructureExtensionsDuringScan" : 0,
      "numberOfFilesScheduledForIndexingAfterScan" : 0
    },
    "scanningStatistics" : [ {
      "providerName" : "JDK 17 /Users/wangxt/Library/Java/JavaVirtualMachines/corretto-17.0.10/Contents/Home",
      "numberOfScannedFiles" : 42616,
      "numberOfSkippedFiles" : 0,
      "numberOfFilesForIndexing" : 0,
      "numberOfFilesFullyIndexedByInfrastructureExtensions" : 0,
      "filesFullyIndexedByInfrastructureExtensions" : [ ],
      "statusTime" : 673986390,
      "totalOneThreadTimeWithPauses" : 1785515917,
      "iterationAndScannersApplicationTime" : 1056309667,
      "filesCheckTime" : 729159416,
      "timeProcessingUpToDateFiles" : 0,
      "timeUpdatingContentLessIndexes" : 0,
      "timeIndexingWithoutContentViaInfrastructureExtension" : 0,
      "roots" : [ ]
    }, {
      "providerName" : "Indexable set contributor 'com.intellij.javaee.ExternalResourcesRootsProvider@6e9f0669' (non-project)",
      "numberOfScannedFiles" : 215,
      "numberOfSkippedFiles" : 4,
      "numberOfFilesForIndexing" : 0,
      "numberOfFilesFullyIndexedByInfrastructureExtensions" : 0,
      "filesFullyIndexedByInfrastructureExtensions" : [ ],
      "statusTime" : 643086542,
      "totalOneThreadTimeWithPauses" : 883608042,
      "iterationAndScannersApplicationTime" : 77082917,
      "filesCheckTime" : 806491709,
      "timeProcessingUpToDateFiles" : 0,
      "timeUpdatingContentLessIndexes" : 0,
      "timeIndexingWithoutContentViaInfrastructureExtension" : 0,
      "roots" : [ ]
    }, {
      "providerName" : "Module 'ssss' (all roots)",
      "numberOfScannedFiles" : 8,
      "numberOfSkippedFiles" : 0,
      "numberOfFilesForIndexing" : 0,
      "numberOfFilesFullyIndexedByInfrastructureExtensions" : 0,
      "filesFullyIndexedByInfrastructureExtensions" : [ ],
      "statusTime" : 137366874,
      "totalOneThreadTimeWithPauses" : 228674375,
      "iterationAndScannersApplicationTime" : 46003042,
      "filesCheckTime" : 178442333,
      "timeProcessingUpToDateFiles" : 0,
      "timeUpdatingContentLessIndexes" : 0,
      "timeIndexingWithoutContentViaInfrastructureExtension" : 0,
      "roots" : [ ]
    }, {
      "providerName" : "Indexable set contributor 'org.jetbrains.kotlin.idea.base.indices.contributors.BuiltInsIndexableSetContributor@12bf6e81' (non-project)",
      "numberOfScannedFiles" : 7,
      "numberOfSkippedFiles" : 0,
      "numberOfFilesForIndexing" : 0,
      "numberOfFilesFullyIndexedByInfrastructureExtensions" : 0,
      "filesFullyIndexedByInfrastructureExtensions" : [ ],
      "statusTime" : 50703041,
      "totalOneThreadTimeWithPauses" : 82275250,
      "iterationAndScannersApplicationTime" : 23485791,
      "filesCheckTime" : 58742792,
      "timeProcessingUpToDateFiles" : 0,
      "timeUpdatingContentLessIndexes" : 0,
      "timeIndexingWithoutContentViaInfrastructureExtension" : 0,
      "roots" : [ ]
    }, {
      "providerName" : "Indexable set contributor 'Scratches & Consoles' (project)",
      "numberOfScannedFiles" : 0,
      "numberOfSkippedFiles" : 0,
      "numberOfFilesForIndexing" : 0,
      "numberOfFilesFullyIndexedByInfrastructureExtensions" : 0,
      "filesFullyIndexedByInfrastructureExtensions" : [ ],
      "statusTime" : 0,
      "totalOneThreadTimeWithPauses" : 14469708,
      "iterationAndScannersApplicationTime" : 4136709,
      "filesCheckTime" : 10000000,
      "timeProcessingUpToDateFiles" : 0,
      "timeUpdatingContentLessIndexes" : 0,
      "timeIndexingWithoutContentViaInfrastructureExtension" : 0,
      "roots" : [ ]
    }, {
      "providerName" : "Indexable set contributor 'org.jetbrains.kotlin.idea.base.indices.contributors.BuiltInsIndexableSetContributor@12bf6e81' (project)",
      "numberOfScannedFiles" : 0,
      "numberOfSkippedFiles" : 0,
      "numberOfFilesForIndexing" : 0,
      "numberOfFilesFullyIndexedByInfrastructureExtensions" : 0,
      "filesFullyIndexedByInfrastructureExtensions" : [ ],
      "statusTime" : 0,
      "totalOneThreadTimeWithPauses" : 14193375,
      "iterationAndScannersApplicationTime" : 4096792,
      "filesCheckTime" : 10067750,
      "timeProcessingUpToDateFiles" : 0,
      "timeUpdatingContentLessIndexes" : 0,
      "timeIndexingWithoutContentViaInfrastructureExtension" : 0,
      "roots" : [ ]
    }, {
      "providerName" : "Indexable set contributor 'Scratches & Consoles' (non-project)",
      "numberOfScannedFiles" : 0,
      "numberOfSkippedFiles" : 0,
      "numberOfFilesForIndexing" : 0,
      "numberOfFilesFullyIndexedByInfrastructureExtensions" : 0,
      "filesFullyIndexedByInfrastructureExtensions" : [ ],
      "statusTime" : 0,
      "totalOneThreadTimeWithPauses" : 13798042,
      "iterationAndScannersApplicationTime" : 4616917,
      "filesCheckTime" : 9128209,
      "timeProcessingUpToDateFiles" : 0,
      "timeUpdatingContentLessIndexes" : 0,
      "timeIndexingWithoutContentViaInfrastructureExtension" : 0,
      "roots" : [ ]
    }, {
      "providerName" : "Indexable set contributor 'com.intellij.javaee.ExternalResourcesRootsProvider@6e9f0669' (project)",
      "numberOfScannedFiles" : 0,
      "numberOfSkippedFiles" : 0,
      "numberOfFilesForIndexing" : 0,
      "numberOfFilesFullyIndexedByInfrastructureExtensions" : 0,
      "filesFullyIndexedByInfrastructureExtensions" : [ ],
      "statusTime" : 0,
      "totalOneThreadTimeWithPauses" : 13696041,
      "iterationAndScannersApplicationTime" : 4502500,
      "filesCheckTime" : 9174083,
      "timeProcessingUpToDateFiles" : 0,
      "timeUpdatingContentLessIndexes" : 0,
      "timeIndexingWithoutContentViaInfrastructureExtension" : 0,
      "roots" : [ ]
    } ]
  }
}